{
    "key": "group_64b152fb2a111",
    "title": "ICS Calendar",
    "fields": [
        {
            "key": "field_64b162acbc757",
            "label": "Calendar Name",
            "name": "aie_calendar_name",
            "aria-label": "",
            "type": "text",
            "instructions": "This is the name of the calendar that shows up in Outlook and other calendar applications.",
            "required": 1,
            "conditional_logic": 0,
            "wrapper": {
                "width": "",
                "class": "",
                "id": ""
            },
            "default_value": "",
            "maxlength": "",
            "placeholder": "",
            "prepend": "",
            "append": ""
        },
        {
            "key": "field_64b152fb30814",
            "label": "Event List",
            "name": "aie_event_list",
            "aria-label": "",
            "type": "repeater",
            "instructions": "",
            "required": 0,
            "conditional_logic": 0,
            "wrapper": {
                "width": "",
                "class": "",
                "id": ""
            },
            "acfe_repeater_stylised_button": 0,
            "layout": "block",
            "pagination": 0,
            "min": 0,
            "max": 0,
            "collapsed": "",
            "button_label": "Add Row",
            "rows_per_page": 20,
            "sub_fields": [
                {
                    "key": "field_64b152fb31a65",
                    "label": "Event Name",
                    "name": "aie_event_name",
                    "aria-label": "",
                    "type": "text",
                    "instructions": "",
                    "required": 1,
                    "conditional_logic": 0,
                    "wrapper": {
                        "width": "",
                        "class": "",
                        "id": ""
                    },
                    "default_value": "",
                    "maxlength": "",
                    "placeholder": "",
                    "prepend": "",
                    "append": "",
                    "parent_repeater": "field_64b152fb30814"
                },
                {
                    "key": "field_64b152fb31aa2",
                    "label": "Event Start Time and Date",
                    "name": "aie_event_start",
                    "aria-label": "",
                    "type": "date_time_picker",
                    "instructions": "",
                    "required": 1,
                    "conditional_logic": 0,
                    "wrapper": {
                        "width": "",
                        "class": "",
                        "id": ""
                    },
                    "display_format": "M jS, g:i A",
                    "return_format": "YmdTHis",
                    "first_day": 1,
                    "placeholder": "",
                    "min_date": "",
                    "max_date": "",
                    "min_time": "",
                    "max_time": "",
                    "no_weekends": 0,
                    "min_hour": "",
                    "max_hour": "",
                    "min_min": "",
                    "max_min": "",
                    "min_sec": "",
                    "max_sec": "",
                    "required_message": "",
                    "parent_repeater": "field_64b152fb30814"
                },
                {
                    "key": "field_64b152fb31ade",
                    "label": "Event End Time and Date",
                    "name": "aie_event_end",
                    "aria-label": "",
                    "type": "date_time_picker",
                    "instructions": "",
                    "required": 0,
                    "conditional_logic": 0,
                    "wrapper": {
                        "width": "",
                        "class": "",
                        "id": ""
                    },
                    "display_format": "M jS, g:i A",
                    "return_format": "YmdTHis",
                    "first_day": 1,
                    "placeholder": "",
                    "min_date": "",
                    "max_date": "",
                    "min_time": "",
                    "max_time": "",
                    "no_weekends": 0,
                    "min_hour": "",
                    "max_hour": "",
                    "min_min": "",
                    "max_min": "",
                    "min_sec": "",
                    "max_sec": "",
                    "parent_repeater": "field_64b152fb30814"
                },
                {
                    "key": "field_64b152fb31b19",
                    "label": "Event Location",
                    "name": "aie_event_location",
                    "aria-label": "",
                    "type": "text",
                    "instructions": "",
                    "required": 0,
                    "conditional_logic": 0,
                    "wrapper": {
                        "width": "",
                        "class": "",
                        "id": ""
                    },
                    "default_value": "",
                    "maxlength": "",
                    "placeholder": "",
                    "prepend": "",
                    "append": "",
                    "parent_repeater": "field_64b152fb30814"
                },
                {
                    "key": "field_64b152fb31b55",
                    "label": "Event Description",
                    "name": "aie_event_description",
                    "aria-label": "",
                    "type": "textarea",
                    "instructions": "",
                    "required": 0,
                    "conditional_logic": 0,
                    "wrapper": {
                        "width": "",
                        "class": "",
                        "id": ""
                    },
                    "default_value": "",
                    "maxlength": "",
                    "rows": "",
                    "placeholder": "",
                    "new_lines": "",
                    "parent_repeater": "field_64b152fb30814",
                    "acfe_textarea_code": 0
                }
            ]
        },
        {
            "key": "field_65d775d71afbf",
            "label": "Spacing",
            "name": "spacing",
            "aria-label": "",
            "type": "clone",
            "instructions": "",
            "required": 0,
            "conditional_logic": 0,
            "wrapper": {
                "width": "",
                "class": "",
                "id": ""
            },
            "clone": [
                "group_65d3ca63dd6e0"
            ],
            "display": "seamless",
            "layout": "block",
            "prefix_label": 0,
            "prefix_name": 0,
            "acfe_seamless_style": 0,
            "acfe_clone_modal": 0,
            "acfe_clone_modal_close": 0,
            "acfe_clone_modal_button": "",
            "acfe_clone_modal_size": "large"
        }
    ],
    "location": [
        [
            {
                "param": "block",
                "operator": "==",
                "value": "butler\/ics-events"
            }
        ]
    ],
    "menu_order": 0,
    "position": "normal",
    "style": "default",
    "label_placement": "top",
    "instruction_placement": "label",
    "hide_on_screen": "",
    "active": true,
    "description": "",
    "show_in_rest": 0,
    "acfe_display_title": "",
    "acfe_autosync": [
        "json"
    ],
    "acfe_form": 0,
    "acfe_meta": "",
    "acfe_note": "",
    "modified": 1709051629
}
